pipeline/__init__.py
pipeline/version.py
pipeline/domain/__init__.py
pipeline/domain/entity.py
pipeline/domain/pipeline.py
pipeline/domain/value_obj.py
pipeline_generator-0.0.2.dist-info/LICENSE
pipeline_generator-0.0.2.dist-info/METADATA
pipeline_generator-0.0.2.dist-info/WHEEL
pipeline_generator-0.0.2.dist-info/top_level.txt
pipeline_generator-0.0.2.dist-info/RECORD
