Metadata-Version: 2.1
Name: pipeline-generator
Version: 0.0.2
Summary: A pipeline generator in python
Author: wangziling100
Author-email: wangziling100@163.com
Classifier: Programming Language :: Python :: 3
Classifier: License :: OSI Approved :: MIT License
License-File: LICENSE
